ludolph_erigones
