Metadata-Version: 1.1
Name: ludolph-erigones
Version: 2.0
Summary: Ludolph: Erigones SDDC API plugin
Home-page: https://github.com/erigones/ludolph-erigones/
Author: Erigones
Author-email: erigones [at] erigones.com
License: MIT
Platform: any
Classifier: Environment :: Console
Classifier: Environment :: Plugins
Classifier: Intended Audience :: Developers
Classifier: Intended Audience :: System Administrators
Classifier: License :: OSI Approved :: MIT License
Classifier: Operating System :: MacOS
Classifier: Operating System :: POSIX
Classifier: Operating System :: Unix
Classifier: Programming Language :: Python
Classifier: Programming Language :: Python :: 2
Classifier: Programming Language :: Python :: 3
Classifier: Topic :: Communications :: Chat
Classifier: Topic :: Utilities
